ratom/__init__.py
ratom/all.py
ratom/aptget.py
ratom/clamav.py
ratom/common.py
ratom/conda.py
ratom/cpanm.py
ratom/freebsd.py
ratom/gem.py
ratom/geoip.py
ratom/git.py
ratom/homebrew.py
ratom/macos.py
ratom/macos_microsoft.py
ratom/msf.py
ratom/npm.py
ratom/perlbrew.py
ratom/pip.py
ratom/pyenv.py
ratom/rbenv.py
ratom/yum.py
ratom-3.0.0.dist-info/METADATA
ratom-3.0.0.dist-info/RECORD
ratom-3.0.0.dist-info/WHEEL
ratom-3.0.0.dist-info/entry_points.txt
ratom-3.0.0.dist-info/top_level.txt
