Metadata-Version: 2.1
Name: ratom
Version: 3.0.0
Summary: Rage Against The Outdated Machine
Home-page: https://github.com/qtfkwk/ratom
Author: qtfkwk
Author-email: qtfkwk+ratom@gmail.com
License: UNKNOWN
Platform: UNKNOWN
Classifier: Development Status :: 4 - Beta
Classifier: Environment :: Console
Classifier: Intended Audience :: End Users/Desktop
Classifier: Intended Audience :: Developers
Classifier: Intended Audience :: System Administrators
Classifier: License :: OSI Approved :: BSD License
Classifier: Topic :: Utilities
Classifier: Topic :: Software Development :: Libraries :: Python Modules
Classifier: Programming Language :: Python :: 2.7
Requires-Dist: blessings
Requires-Dist: bs4
Requires-Dist: kron
Requires-Dist: requests
